buchi/__init__.py
buchi/agent.py
buchi/backup.py
buchi/cli.py
buchi/logging.py
buchi/persistence/__init__.py
buchi/persistence/json_storage.py
buchi/tools/__init__.py
buchi/tools/file_ops.py
buchi_cli-0.1.2.dist-info/licenses/LICENSE
buchi_cli-0.1.2.dist-info/METADATA
buchi_cli-0.1.2.dist-info/WHEEL
buchi_cli-0.1.2.dist-info/entry_points.txt
buchi_cli-0.1.2.dist-info/top_level.txt
buchi_cli-0.1.2.dist-info/RECORD
