Metadata-Version: 2.4
Name: buchi-cli
Version: 0.1.2
Summary: AI coding assistant powered by Ollama
Author-email: Casey Dale Siatong <daledev07@gmail.com>
License: MIT License
Project-URL: Homepage, https://github.com/DaleStack/buchi
Project-URL: Repository, https://github.com/DaleStack/buchi.git
Project-URL: Issues, https://github.com/DaleStack/buchi/issues
Keywords: ai,cli,coding-assistant,ollama,llm
Classifier: Development Status :: 4 - Beta
Classifier: Environment :: Console
Classifier: Intended Audience :: Developers
Classifier: Programming Language :: Python :: 3
Classifier: Programming Language :: Python :: 3.10
Classifier: Programming Language :: Python :: 3.11
Classifier: Topic :: Software Development :: Code Generators
Requires-Python: >=3.10
License-File: LICENSE
Requires-Dist: typer>=0.12.0
Requires-Dist: rich>=13.0.0
Requires-Dist: requests>=2.32.0
Requires-Dist: langchain>=1.0.0
Requires-Dist: langchain-community>=0.4.0
Requires-Dist: langchain-ollama>=1.0.0
Requires-Dist: langchain-core>=1.0.0
Requires-Dist: langgraph>=1.0.0
Requires-Dist: langgraph-prebuilt>=1.0.0
Requires-Dist: ollama>=0.6.0
Requires-Dist: pydantic>=2.10.0
Requires-Dist: python-dotenv>=1.0.0
Requires-Dist: sqlalchemy>=2.0.0
Provides-Extra: dev
Requires-Dist: pytest>=8.0.0; extra == "dev"
Requires-Dist: pytest-cov>=5.0.0; extra == "dev"
Requires-Dist: ruff>=0.3.0; extra == "dev"
Requires-Dist: build>=1.0.0; extra == "dev"
Requires-Dist: types-requests; extra == "dev"
Requires-Dist: types-PyYAML; extra == "dev"
Dynamic: license-file
